atlasq/__init__.py
atlasq/queryset/__init__.py
atlasq/queryset/exceptions.py
atlasq/queryset/index.py
atlasq/queryset/manager.py
atlasq/queryset/node.py
atlasq/queryset/queryset.py
atlasq/queryset/transform.py
atlasq/queryset/visitor.py
atlasq-0.15.0.dist-info/LICENSE.txt
atlasq-0.15.0.dist-info/METADATA
atlasq-0.15.0.dist-info/WHEEL
atlasq-0.15.0.dist-info/top_level.txt
atlasq-0.15.0.dist-info/RECORD
