Metadata-Version: 2.1
Name: atlasq
Version: 0.15.0
Summary: Query proxy that allows the usage of AtlasSearch with mongoengine specific syntax
Maintainer-email: Simone Berni <s.berni@certego.net>
License: MIT License
Project-URL: homepage, https://github.com/certego/atlasq
Project-URL: repository, https://github.com/certego/atlasq
Project-URL: documentation, https://github.com/certego/atlasq/README.md
Project-URL: source, https://github.com/certego/atlasq
Project-URL: tracker, https://github.com/certego/atlasq/issues
Keywords: certego,atlas,mongoengine,python,search,textsearch,atlassearch
Classifier: Development Status :: 3 - Alpha
Classifier: Intended Audience :: Developers
Classifier: License :: OSI Approved :: BSD License
Classifier: Programming Language :: Python :: 3.6
Classifier: Programming Language :: Python :: 3.7
Classifier: Programming Language :: Python :: 3.8
Classifier: Programming Language :: Python :: 3.9
Classifier: Programming Language :: Python :: 3.10
Classifier: Topic :: Software Development :: Libraries :: Python Modules
Requires-Python: >=3.6
License-File: LICENSE.txt
Requires-Dist: mongoengine >=0.22.0
Requires-Dist: requests >=2.18.0
Provides-Extra: test
Requires-Dist: black ==23.7.0 ; extra == 'test'
Requires-Dist: isort ==5.10.1 ; extra == 'test'
Requires-Dist: pylint ==2.17.4 ; extra == 'test'
Requires-Dist: flake8 ==4.0.1 ; extra == 'test'
Requires-Dist: pre-commit ==3.3.2 ; extra == 'test'
Requires-Dist: tox ==4.6.4 ; extra == 'test'
Requires-Dist: tox-gh-actions ==3.1.1 ; extra == 'test'
Requires-Dist: codecov ==2.1.12 ; extra == 'test'
Requires-Dist: coverage ==7.2.7 ; extra == 'test'
Requires-Dist: mongomock ==4.1.2 ; extra == 'test'
